mass_pkdv/__init__.py
mass_pkdv/run_mass.py
mass_pkdv/bin/mass_pkdv.exe
mass_pkdv/bin_dll/libgcc_s_dw2-1.dll
mass_pkdv/bin_dll/libstdc++-6.dll
mass_pkdv-0.1.1.dist-info/METADATA
mass_pkdv-0.1.1.dist-info/WHEEL
mass_pkdv-0.1.1.dist-info/top_level.txt
mass_pkdv-0.1.1.dist-info/RECORD
