Metadata-Version: 2.4
Name: mass-pkdv
Version: 0.1.1
Summary: Product Kernel Density Visualization (pKDV) algorithm
Home-page: https://github.com/MASS-group/MASS
Author: MASS-group
Author-email: 
Classifier: Programming Language :: Python :: 3
Classifier: License :: OSI Approved :: MIT License
Classifier: Operating System :: OS Independent
Requires-Python: >=3.7
Dynamic: author
Dynamic: classifier
Dynamic: description
Dynamic: description-content-type
Dynamic: home-page
Dynamic: requires-python
Dynamic: summary
